Workbook

Sheet Остатки счетам баланса за 3 кв
C1: Вариант 25 | E1: Прокопьев Даниил | H1: 932204
B2: № счета | C2: Наименование | D2: Актив | E2: Пассив
B3: 1 | C3: Основные средства | D3: 3796966.7
B4: 2 | C4: Амортизация ОС | D4: 11363
B5: 50 | C5: Касса | D5: 11899.59
B6: 51 | C6: Расчетный счет | D6: 151321.74
B7: 55 | C7: Специальные счета в банках | D7: 27500
B8: 62 | C8: Покупатели и заказчики | D8: 1024000
B9: 71 | C9: Подотчетные лица | D9: 305.97
B10: 66 | C10: Краткосрочные кредиты и займы | E10: 19748.16
B11: 68 | C11: Налоги и сборы | E11: 114466.7
B12: 69 | C12: Соцстрахование | E12: 43480.97
B13: 80 | C13: Уставный капитал | E13: 4569350.3
B14: 82 | C14: Резервный капитал | E14: 132500
B15: 84 | C15: Нераспределенная прибыль | E15: 121084.86
C16: Итого | D16: 5000631 | E16: 5000631

Sheet Книга учета хоз. операций
B1: Вариант 25 | D1: Прокопьев Даниил | G1: 932204
F2: НДС на момент 14.04.2026 = 22%
F3: Однако мы берем НДС-20% т.к в задаче явно указаны даты до 26 года
B4: Книга учета хозяйственных операций ООО «ША»
B5: 1 Операция | C5: Оплата от покупателя, погашение кредита и процентов
B6: № | C6: Дата | D6: Наименование операции | E6: Дебет сч. | F6: Кредит сч. | G6: Сумма, руб.
B7: 1 | C7: 45931 | D7: Получена 100% оплата от покупателя за продукцию 3 кв. | E7: 51 | F7: 62 | G7: ='Остатки счетам баланса за 3 кв'!D8 -> 1024000
B8: 2 | C8: 45931 | D8: Начислены проценты по краткосрочному кредиту | E8: 91-2 | F8: 66-2 | G8: =1922 -> 1922 | H8: Проценты прямо из условия
B9: 3 | C9: 45931 | D9: Погашен краткосрочный кредит | E9: 66-1 | F9: 51 | G9: ='Остатки счетам баланса за 3 кв'!E10 -> 19748.16
B10: 4 | C10: 45931 | D10: Уплачены проценты по кредиту | E10: 66-2 | F10: 51 | G10: =G8 -> 1922 | H10: Та же сумма процентов
B11: 5 | C11: 45931 | D11: Начислен налог на имущество | E11: 99-3 | F11: 68-8 | G11: =(2.2%/4)*('Остатки счетам баланса за 3 кв'!D3-'Остатки счетам баланса за 3 кв'!D4) -> 20820.82
B12: 6 | C12: 45931 | D12: Уплачен налог на имущество | E12: 68-8 | F12: 51 | G12: =G11 -> 20820.82
B15: 2 Операция | C15: Командировка Таболкина
B16: № | C16: Дата | D16: Наименование операции | E16: Дебет сч. | F16: Кредит сч. | G16: Сумма, руб.
B17: 7 | C17: 45948 | D17: Получены наличные с расчётного счёта для выдачи аванса Таболкину Ф.И. | E17: 50 | F17: 51 | G17: =38250 -> 38250
B18: 8 | C18: 45948 | D18: Выданы деньги под отчет Таболкину Ф.И. | E18: 71 | F18: 50 | G18: =33700 -> 33700 | H18: Выданный аванс
B19: 9 | C19: 45952 | D19: Списаны командировочные расходы без НДС | E19: 44 | F19: 71 | G19: =G17-G21 -> 37748 | H19: Общий авансовый отчет 38250, из него НДС 502
B20: 10 | C20: 45952 | D20: Выделен НДС по командировочным расходам | E20: 19 | F20: 71 | G20: =502 -> 502 | H20: НДС выделяется отдельно
B21: 11 | C21: 45952 | D21: НДС по командировочным принят к вычету | E21: 68-2 | F21: 19 | G21: =G20 -> 502
B22: 12 | C22: 45953 | D22: Возмещен перерасход подотчетному лицу | E22: 71 | F22: 50 | G22: =G17-G18 -> 4550 | H22: Подотчетное лицо израсходовало по авансовому отчету всего 38250, а не 37748.
B25: 3 Операция | C25: Покупка оборудования и монтаж
B26: № | C26: Дата | D26: Наименование операции | E26: Дебет сч. | F26: Кредит сч. | G26: Сумма, руб.
B27: 13 | C27: 45980 | D27: Отражена стоимость оборудования, требующего монтажа, без НДС | E27: 07 | F27: 60 | G27: =G29/1.2 -> 188990 | H27: Из общей суммы покупки выделяем стоимость без НДС
B28: 14 | C28: 45980 | D28: Выделен входной НДС по оборудованию | E28: 19-1 | F28: 60 | G28: =G29-G27 -> 37798 | H28: Это не платеж, а выделение входного НДС
B29: 15 | C29: 45980 | D29: Оплачено оборудование поставщику | E29: 60 | F29: 51 | G29: 226788 | H29: Платим поставщику всю сумму по платежному поручению
B30: 16 | C30: 45980 | D30: Отражена стоимость монтажа оборудования | E30: 07 | F30: 60 | G30: =28000 -> 28000 | H30: В условии прямо сказано: монтаж 28000 без НДС
B31: 17 | C31: 45980 | D31: Оплачен монтаж оборудования | E31: 60 | F31: 51 | G31: =G30 -> 28000 | H31: Оплата подрядчику за монтаж
B32: 18 | C32: 45980 | D32: Сформированы капитальные вложения по оборудованию | E32: 08-4 | F32: 07 | G32: =G27+G30 -> 216990 | H32: Полная первоначальная стоимость без НДС: оборудование + монтаж
H33: Оборудование находится на регистрации в ЕГРОС поэтому мы не доводим его до ввода на 01 счет
B35: 4 Операция | C35: Обналичивание денег и выдача Фокину
B36: № | C36: Дата | D36: Наименование операции | E36: Дебет сч. | F36: Кредит сч. | G36: Сумма, руб.
B37: 19 | C37: 45965 | D37: Получены наличные из банка по денежному чеку | E37: 50 | F37: 51 | G37: 45000 | H37: Из-за самого факта “сняли наличные в банке и выдали их под отчет” налог платить не нужно.
B38: 20 | C38: 45965 | D38: Выданы деньги под отчет Фокину Я.Б. | E38: 71 | F38: 50 | G38: =G37 -> 45000 | H38: Это движение денег внутри компании: 51 → 50 → 71. Само по себе оно не образует ни НДС, ни НДФЛ
B41: 5 Операция | C41: Канцтовары, материалы и списание материалов в производство
B42: № | C42: Дата | D42: Наименование операции | E42: Дебет сч. | F42: Кредит сч. | G42: Сумма, руб.
B43: 21 | C43: 45978 | D43: Списаны канцтовары на общехозяйственные расходы | E43: 26 | F43: 71 | G43: =40725 -> 40725 | H43: Списаны канцтовары на общехозяйственные расходы
B44: 22 | C44: 45978 | D44: Оформлена чековая книжка / лимит под расчетный чек | E44: 55-2 | F44: 51 | G44: =205800 -> 205800 | H44: Оформлена чековая книжка / лимит под расчетный чек
B45: 23 | C45: 45978 | D45: Оплачены основные материалы расчетным чеком | E45: 60 | F45: 55-2 | G45: =G44 -> 205800 | H45: Оплачены основные материалы расчетным чеком
B46: 24 | C46: 45978 | D46: Оприходованы основные материалы без НДС | E46: 10 | F46: 60 | G46: =G45/1.2 -> 171500 | H46: Оприходованы основные материалы без НДС
B47: 25 | C47: 45978 | D47: Выделен НДС по основным материалам | E47: 19-3 | F47: 60 | G47: =G44-G46 -> 34300 | H47: Выделен НДС по основным материалам
B48: 26 | C48: 45978 | D48: Списаны основные материалы в производство | E48: 20 | F48: 10 | G48: 170547 | H48: Списаны основные материалы в производство
B49: 27 | C49: 45978 | D49: НДС по израсходованным материалам принят к вычету | E49: 68-2 | F49: 19-3 | G49: =G47*G48/G46 -> 34109.4 | H49: НДС по израсходованным материалам принят к вычету
B50: 28 | C50: 46022 | D50: Начислена амортизация ОС, используемых при обработке материалов | E50: 20 | F50: 02 | G50: =2693000/8/4 -> 84156.25 | H50: Начислена амортизация ОС, используемых при обработке материалов
B51: 29 | C51: 46022 | D51: Начислена амортизация оставшихся общехозяйственных ОС | E51: 26 | F51: 02 | G51: =('Остатки счетам баланса за 3 кв'!D3-2693000)*0.05/4 -> 13799.584 | H51: Начислена амортизация оставшихся общехозяйственных ОС
B54: 6 Операция | C54: Реклама
B55: № | C55: Дата | D55: Наименование операции | E55: Дебет сч. | F55: Кредит сч. | G55: Сумма, руб.
B56: 30 | C56: 46010 | D56: Отражены расходы на телерекламу без НДС | E56: 44 | F56: 60 | G56: =G58/1.2 -> 43333.333
B57: 31 | C57: 46010 | D57: Выделен НДС по рекламе | E57: 19-3 | F57: 60 | G57: =G58-G56 -> 8666.6667
B58: 32 | C58: 46010 | D58: Оплачены рекламные услуги | E58: 60 | F58: 51 | G58: =52000 -> 52000
B59: 33 | C59: 46016 | D59: НДС по рекламе принят к вычету | E59: 68-2 | F59: 19-3 | G59: =G58-G56 -> 8666.6667
B62: 7 Операция | C62: Выдача заработной платы
B63: № | C63: Дата | D63: Наименование операции | E63: Дебет сч. | F63: Кредит сч. | G63: Сумма, руб.
B64: 34 | C64: 46015 | D64: Начисление заработной платы по основному производству | E64: 20 | F64: 70 | G64: =291000 -> 291000 | H64: Это зарплата работников, которые непосредственно делают продукцию.
B65: 35 | C65: 46015 | D65: Начисление заработной платы АУП | E65: 26 | F65: 70 | G65: =269820 -> 269820 | H65: Это зарплата административно-управленческого персонала.
B66: 36 | C66: 46015 | D66: Страховые взносы по основному производству | E66: 20 | F66: 69 | G66: =G64*30.2% -> 87882 | H66: На зарплату рабочих предприятие дополнительно начисляет страховые взносы.
B67: 37 | C67: 46015 | D67: Страховые взносы АУП | E67: 26 | F67: 69 | G67: =G65*30.2% -> 81485.64 | H67: Это взносы уже не по рабочим, а по АУП.
B68: 38 | C68: 46015 | D68: НДФЛ по заработной плате | E68: 70 | F68: 68-1 | G68: =((((G65+G64)-((1400+2800+6000)*3))*13%)) -> 68928.6 | H68: работникам уже должны не всю начисленную зарплату, а за минусом НДФЛ; на 68-1 появляется сумма налога к перечислению.
B69: 39 | C69: 46016 | D69: Выплата заработной платы | E69: 70 | F69: 51 | G69: =G64+G65-G68 -> 491891.4 | H69: задолженность по зарплате уменьшается, с расчетного счета уходят деньги работникам.
B70: 40 | C70: 46016 | D70: Выплата страховых взносов | E70: 69 | F70: 51 | G70: =(G64+G65)*30.2% -> 169367.64 | H70: по условию этой строки нет, потому что там сказано только, что выплачена зарплата, а не что перечислены взносы. Однако я решил что взносы так или иначе должны быть выплачены
B71: 41 | C71: 46016 | D71: Выплата НДФЛ | E71: 68-ЕНП | F71: 51 | G71: =G68 -> 68928.6 | H71: Как и со строкой 37, в тексте задания прямо не написано, что НДФЛ перечислен. Однако я решил что он должен быть выплачен
B74: 8 Операция | C74: выпуск 80% готовой продукции
B75: № | C75: Дата | D75: Наименование операции | E75: Дебет сч. | F75: Кредит сч. | G75: Сумма, руб. | H75: Тут всего одна проводка потому что 8 операция по условию — это только: "26.12 получены на склад 80% готовой продукции, изготовленной в 4 кв." Это означает внутреннее перемещение внутри учета: было на 20 как затраты производства, стало на 43 как готовая продукция на складе. То есть здесь одна проводка
B76: 42 | C76: 46017 | D76: Оприходована на склад готовая продукция (80% выпуска 4 кв.) | E76: 43 | F76: 20 | G76: =(G48+G50+G66+G64)*80% -> 506868.2 | H76: Однако у нас осталось 20%, они остаются на 20 счете как незавершенное производство, и я не знаю нужно ли прописывать это как проводку или нет
B79: Закрывающий блок
B80: № | C80: Дата | D80: Наименование операции | E80: Дебет сч. | F80: Кредит сч. | G80: Сумма, руб.
B81: 43 | C81: 46022 | D81: Списаны коммерческие расходы на продажи | E81: 90-2 | F81: 44 | G81: =G56+G19 -> 81081.333
B82: 44 | C82: 46022 | D82: Списаны общехозяйственные расходы на продажи | E82: 90-2 | F82: 26 | G82: =G43+G65+G67+G51 -> 405830.22
B83: 45 | C83: 46022 | D83: Отражен убыток от продаж | E83: 99 | F83: 90-9 | G83: =G81+G82 -> 486911.56 | H83: Потому что в 4 квартале нет выручки по 90-1, а расходы периода есть. По учебнику результат по 90 и 91 в конце месяца переносится на 99.
B84: 46 | C84: 46022 | D84: Отражен прочий убыток по процентам | E84: 99 | F84: 91-9 | G84: =G8 -> 1922 | H84: Они шли на 91-2, значит закрываются как прочий убыток на 99. Счет 91 предназначен для прочих доходов и расходов, а проценты к уплате попадают в операционные/прочие расходы.
B85: 47 | C85: 46022 | D85: Списан итоговый убыток отчетного периода на счет 84-1 | E85: 84-1 | F85: 99 | G85: =G83+G84+G11 -> 509654.38 | H85: И его уже переносим на 84-1 как непокрытый убыток отчетного периода, потому что по учебнику чистая прибыль/убыток счета 99 в конце года списывается на 84.

Sheet ОСБ
B2: № пп | C2: №№ счет - кор. счет | D2: Сальдо начальное | F2: Обороты | H2: Сальдо исходящее
D3: Д | E3: К | F3: Д | G3: К | H3: Д | I3: К
B4: 1 | C4: 01* | D4: ='Остатки счетам баланса за 3 кв'!D3 -> 3796966.7 | H4: =SUM(D4) -> 3796966.7 | J4: оборудование еще на регистрации, поэтому 01/08 пока нет.
B5: 2 | C5: 02-20 | G5: ='Книга учета хоз. операций'!G50 -> 84156.25
B6: 3 | C6: 02-26 | G6: ='Книга учета хоз. операций'!G51 -> 13799.584
B7: 4 | C7: 02* | E7: ='Остатки счетам баланса за 3 кв'!D4 -> 11363 | G7: =SUM(G5:G6) -> 97955.834 | I7: =E7+G7 -> 109318.83
B8: 5 | C8: 07-60 | F8: ='Книга учета хоз. операций'!G27 -> 188990
B9: 6 | C9: 07-60 | F9: ='Книга учета хоз. операций'!G30 -> 28000
B10: 7 | C10: 07-08-4 | G10: ='Книга учета хоз. операций'!G32 -> 216990
B11: 8 | C11: 07* | F11: =SUM(F8:F9) -> 216990 | G11: =SUM(G10) -> 216990
B12: 9 | C12: 08-04-07 | F12: =G10 -> 216990
B13: 10 | C13: 08* | F13: =SUM(F12) -> 216990 | H13: =SUM(F13) -> 216990
B14: 11 | C14: 10-60 | F14: ='Книга учета хоз. операций'!G46 -> 171500
B15: 12 | C15: 10-20 | G15: ='Книга учета хоз. операций'!G48 -> 170547
B16: 13 | C16: 10* | F16: =SUM(F14) -> 171500 | G16: =SUM(G15) -> 170547 | H16: =F16-G16 -> 953
B17: 14 | C17: 19-71 | F17: ='Книга учета хоз. операций'!G20 -> 502
B18: 15 | C18: 19-1-60 | F18: ='Книга учета хоз. операций'!G28 -> 37798
B19: 16 | C19: 19-3-60 | F19: ='Книга учета хоз. операций'!G47 -> 34300
B20: 17 | C20: 19-3-60 | F20: ='Книга учета хоз. операций'!G59 -> 8666.6667
B21: 18 | C21: 19-68-2 | G21: ='Книга учета хоз. операций'!G21 -> 502
B22: 19 | C22: 19-2-68-2 | G22: ='Книга учета хоз. операций'!G49 -> 34109.4
B23: 20 | C23: 19-3-68-2 | G23: ='Книга учета хоз. операций'!G59 -> 8666.6667
B24: 21 | C24: 19* | F24: =SUM(F17:F20) -> 81266.667 | G24: =SUM(G21:G23) -> 43278.067 | H24: =F24-G24 -> 37988.6 | J24: По оборудованию НДС пока останется на 19, если мы не принимаем его к вычету до регистрации.
B25: 22 | C25: 20-10 | F25: ='Книга учета хоз. операций'!G48 -> 170547
B26: 23 | C26: 20-70 | F26: ='Книга учета хоз. операций'!G64 -> 291000
B27: 24 | C27: 20-69 | F27: ='Книга учета хоз. операций'!G66 -> 87882
B28: 25 | C28: 20-02 | F28: ='Книга учета хоз. операций'!G50 -> 84156.25
B29: 26 | C29: 20-43 | G29: ='Книга учета хоз. операций'!G76 -> 506868.2
B30: 27 | C30: 20* | F30: =SUM(F25:F28) -> 633585.25 | G30: =SUM(G29) -> 506868.2 | H30: =F30-G30 -> 126717.05
B31: 28 | C31: 26-71 | F31: ='Книга учета хоз. операций'!G43 -> 40725
B32: 29 | C32: 26-70 | F32: ='Книга учета хоз. операций'!G65 -> 269820
B33: 30 | C33: 26-69 | F33: ='Книга учета хоз. операций'!G67 -> 81485.64
B34: 31 | C34: 26-02 | F34: ='Книга учета хоз. операций'!G51 -> 13799.584
B35: 32 | C35: 26-90-2 | G35: ='Книга учета хоз. операций'!G82 -> 405830.22
B36: 33 | C36: 26* | F36: =SUM(F31:F34) -> 405830.22 | G36: =SUM(G35) -> 405830.22 | H36: =F36-G36 -> 0
B37: 34 | C37: 43-20 | F37: ='Книга учета хоз. операций'!G76 -> 506868.2
B38: 35 | C38: 43* | F38: =SUM(F37) -> 506868.2 | H38: =SUM(F38) -> 506868.2
B39: 36 | C39: 44-71 | F39: ='Книга учета хоз. операций'!G19 -> 37748
B40: 37 | C40: 44-60 | F40: ='Книга учета хоз. операций'!G56 -> 43333.333
B41: 38 | C41: 44-90-2 | G41: ='Книга учета хоз. операций'!G81 -> 81081.333
B42: 39 | C42: 44* | F42: =SUM(F39:F40) -> 81081.333 | G42: =SUM(G41) -> 81081.333 | H42: =F42-G41 -> 0
B43: 40 | C43: 50-51 | F43: ='Книга учета хоз. операций'!G37 -> 45000
B44: 41 | C44: 50-71 | G44: ='Книга учета хоз. операций'!G38 -> 45000
B45: 42 | C45: 50-71 | G45: ='Книга учета хоз. операций'!G18 -> 33700
B46: 43 | C46: 50-71 | G46: ='Книга учета хоз. операций'!G22 -> 4550
B47: 44 | C47: 50-55 | F47: ='Книга учета хоз. операций'!G17 -> 38250
B48: 45 | C48: 50* | D48: ='Остатки счетам баланса за 3 кв'!D5 -> 11899.59 | F48: =SUM(F43:F47) -> 83250 | G48: =SUM(G44:G46) -> 83250 | H48: =D48+F48-G48 -> 11899.59
B49: 46 | C49: 51-62 | F49: ='Книга учета хоз. операций'!G7 -> 1024000
B50: 47 | C50: 51-68-8 | G50: ='Книга учета хоз. операций'!G12 -> 20820.82
B51: 48 | C51: 51-66-1 | G51: ='Книга учета хоз. операций'!G9 -> 19748.16
B52: 49 | C52: 51-66-2 | G52: ='Книга учета хоз. операций'!G10 -> 1922
B53: 50 | C53: 51-50 | G53: ='Книга учета хоз. операций'!G37 -> 45000
B54: 51 | C54: 51-55-2 | G54: ='Книга учета хоз. операций'!G44 -> 205800
B55: 52 | C55: 51-60 | G55: ='Книга учета хоз. операций'!G29 -> 226788
B56: 53 | C56: 51-60 | G56: ='Книга учета хоз. операций'!G31 -> 28000
B57: 54 | C57: 51-60 | G57: ='Книга учета хоз. операций'!G58 -> 52000
B58: 55 | C58: 51-70 | G58: ='Книга учета хоз. операций'!G69 -> 491891.4
B59: 56 | C59: 51-69 | G59: ='Книга учета хоз. операций'!G70 -> 169367.64
B60: 57 | C60: 51-68-ЕНП | G60: ='Книга учета хоз. операций'!G71 -> 68928.6
B61: 58 | C61: 51-50 | G61: ='Книга учета хоз. операций'!G17 -> 38250
B62: 59 | C62: 51* | D62: ='Остатки счетам баланса за 3 кв'!D6 -> 151321.74 | F62: =SUM(F49) -> 1024000 | G62: =SUM(G50:G61) -> 1368516.6 | I62: =G62-F62-D62 -> 193194.88
B63: 60 | C63: 55-2-51 | F63: ='Книга учета хоз. операций'!G44 -> 205800
B64: 61 | C64: 55-2-60 | G64: ='Книга учета хоз. операций'!G45 -> 205800
B65: 62 | C65: 55* | D65: ='Остатки счетам баланса за 3 кв'!D7 -> 27500 | F65: =SUM(F63) -> 205800 | G65: =SUM(G64) -> 205800 | H65: =D65+F65-G65 -> 27500
B66: 63 | C66: 60-55-2 | F66: ='Книга учета хоз. операций'!G45 -> 205800
B67: 64 | C67: 60-51 | F67: ='Книга учета хоз. операций'!G29 -> 226788
B68: 65 | C68: 60-51 | F68: ='Книга учета хоз. операций'!G31 -> 28000
B69: 66 | C69: 60-51 | F69: ='Книга учета хоз. операций'!G58 -> 52000
B70: 67 | C70: 60-10 | G70: ='Книга учета хоз. операций'!G46 -> 171500
B71: 68 | C71: 60-19-3 | G71: ='Книга учета хоз. операций'!G47 -> 34300
B72: 69 | C72: 60-07 | G72: ='Книга учета хоз. операций'!G27 -> 188990
B73: 70 | C73: 60-19-1 | G73: ='Книга учета хоз. операций'!G28 -> 37798
B74: 71 | C74: 60-07 | G74: ='Книга учета хоз. операций'!G30 -> 28000
B75: 72 | C75: 60-44 | G75: ='Книга учета хоз. операций'!G56 -> 43333.333
B76: 73 | C76: 60-19-3 | G76: ='Книга учета хоз. операций'!G57 -> 8666.6667
B77: 74 | C77: 60* | F77: =SUM(F66:F69) -> 512588 | G77: =SUM(G70:G76) -> 512588 | H77: =F77-G77 -> 0
B78: 75 | C78: 62-51 | G78: ='Книга учета хоз. операций'!G7 -> 1024000
B79: 76 | C79: 62* | D79: ='Остатки счетам баланса за 3 кв'!D8 -> 1024000 | G79: =SUM(G78) -> 1024000 | H79: =D79-G79 -> 0
B80: 77 | C80: 66-1-51 | F80: ='Книга учета хоз. операций'!G9 -> 19748.16
B81: 78 | C81: 66-2-51 | F81: ='Книга учета хоз. операций'!G10 -> 1922
B82: 79 | C82: 66-2-91-2 | G82: ='Книга учета хоз. операций'!G8 -> 1922
B83: 80 | C83: 66* | E83: ='Остатки счетам баланса за 3 кв'!E10 -> 19748.16 | F83: =SUM(F80:F81) -> 21670.16 | G83: =SUM(G82) -> 1922 | H83: =F83-G83-E83 -> 0
B84: 81 | C84: 68-2-19 | F84: ='Книга учета хоз. операций'!G21 -> 502
B85: 82 | C85: 68-2-19-3 | F85: ='Книга учета хоз. операций'!G49 -> 34109.4
B86: 83 | C86: 68-2-19-3 | F86: ='Книга учета хоз. операций'!G59 -> 8666.6667
B87: 84 | C87: 68-8-51 | F87: ='Книга учета хоз. операций'!G12 -> 20820.82
B88: 85 | C88: 68-ЕНП-51 | F88: ='Книга учета хоз. операций'!G71 -> 68928.6
B89: 86 | C89: 68-1-70 | G89: ='Книга учета хоз. операций'!G68 -> 68928.6
B90: 87 | C90: 68-8-99-3 | G90: ='Книга учета хоз. операций'!G11 -> 20820.82
B91: 88 | C91: 68* | E91: ='Остатки счетам баланса за 3 кв'!E11 -> 114466.7 | F91: =SUM(F84:F88) -> 133027.49 | G91: =SUM(G89:G90) -> 89749.42 | I91: =G91+E91-F91 -> 71188.633
B92: 89 | C92: 69-20 | G92: ='Книга учета хоз. операций'!G66 -> 87882
B93: 90 | C93: 69-26 | G93: ='Книга учета хоз. операций'!G67 -> 81485.64
B94: 91 | C94: 69-51 | F94: ='Книга учета хоз. операций'!G70 -> 169367.64
B95: 92 | C95: 69* | E95: ='Остатки счетам баланса за 3 кв'!E12 -> 43480.97 | F95: =SUM(F94) -> 169367.64 | G95: =SUM(G92:G93) -> 169367.64 | I95: =G95+E95-F95 -> 43480.97
B96: 93 | C96: 70-20 | G96: ='Книга учета хоз. операций'!G64 -> 291000
B97: 94 | C97: 70-26 | G97: ='Книга учета хоз. операций'!G65 -> 269820
B98: 95 | C98: 70-68-1 | F98: ='Книга учета хоз. операций'!G68 -> 68928.6
B99: 96 | C99: 70-51 | F99: ='Книга учета хоз. операций'!G69 -> 491891.4
B100: 97 | C100: 70* | F100: =SUM(F98:F99) -> 560820 | G100: =SUM(G96:G97) -> 560820 | H100: =F100-G100 -> 0
B101: 98 | C101: 71-50 | F101: ='Книга учета хоз. операций'!G18 -> 33700
...

Sheet Форма 1
C2: Актив | D2: Код показателя | E2: На начало отчетного года | F2: На конец отчетного периода
C3: 1 | D3: 2 | E3: 3 | F3: 4
C4: I. ВНЕОБОРОТНЫЕ АКТИВЫ Основные средства (01, 02) | D4: 120 | E4: =ОСБ!D4-ОСБ!E7 -> 3785603.7 | F4: =ОСБ!H4-ОСБ!I7 -> 3687647.9
C5: Незавершенное строительство (07, 08, 016) | D5: 130 | E5: =ОСБ!D11+ОСБ!D13 -> 0 | F5: =ОСБ!H11+ОСБ!H13 -> 216990
C6: Итого по разделу I | D6: 190 | E6: =SUM(E4:E5) -> 3785603.7 | F6: =SUM(F4:F5) -> 3904637.9
C7: II. ОБОРОТНЫЕ АКТИВЫ в том числе: сырье, материалы и другие аналогичные ценности (10, 14, 16) | D7: 211 | E7: =ОСБ!D16 -> 0 | F7: =ОСБ!H16 -> 953
C8: затраты в незавершенном производстве (20, 21, 23, 29, 44, 46) | D8: 213 | E8: =ОСБ!D30 -> 0 | F8: =ОСБ!H30 -> 126717.05
C9: готовая продукция и товары для перепродажи (16, 41, 43) | D9: 214 | E9: =ОСБ!D38 -> 0 | F9: =ОСБ!H38 -> 506868.2
C10: Налог на добавленную стоимость по приобретенным ценностям (19) | D10: 220 | E10: =ОСБ!D24 -> 0 | F10: =ОСБ!H24 -> 37988.6
C11: в том числе: покупатели и заказчики (62, 63, 76) | D11: 241 | E11: =ОСБ!D79 -> 1024000 | F11: =ОСБ!H79 -> 0
C12: прочие дебиторы (68, 69) | D12: 246 | E12: =ОСБ!D107 -> 305.97 | F12: =ОСБ!H107+ОСБ!H77 -> 4580.97
C13: в том числе: касса (50) | D13: 261 | E13: =ОСБ!D48 -> 11899.59 | F13: =ОСБ!H48 -> 11899.59
C14: расчетные счета (51) | D14: 262 | E14: =ОСБ!D62 -> 151321.74 | F14: =ОСБ!H62 -> 0
C15: прочие денежные средства (55, 57) | D15: 264 | E15: =ОСБ!D65 -> 27500 | F15: =ОСБ!H65 -> 27500
C16: Итого по разделу II | D16: 290 | E16: =SUM(E7:E15) -> 1215027.3 | F16: =SUM(F7:F15) -> 716507.41
C17: БАЛАНС (сумма строк 190+290) | D17: 300 | E17: =E16+E6 -> 5000631 | F17: =F16+F6 -> 4621145.3
C19: Пассив
C20: III. КАПИТАЛ И РЕЗЕРВЫ Уставный капитал (80) | D20: 410 | E20: =ОСБ!E108 -> 4569350.3 | F20: =ОСБ!I108 -> 4569350.3
C21: Резервный капитал (82) | D21: 430 | E21: =ОСБ!E109 -> 132500 | F21: =ОСБ!I109 -> 132500
C22: Нераспределенная прибыль прошлых лет (84-2) | D22: 460 | E22: =ОСБ!E111 -> 121084.86 | F22: =0 -> 0
C23: Непокрытый убыток отчетного года (84-1) | D23: 475 | E23: х | F23: =ОСБ!H111 -> 388569.52
C24: Итого по разделу III | D24: 490 | E24: =SUM(E20:E22) -> 4822935.2 | F24: =F20+F21-F23 -> 4313280.8
C25: V. КРАТКОСРОЧНЫЕ ОБЯЗАТЕЛЬСТВА Займы и кредиты (66) | D25: 610 | E25: =ОСБ!E83 -> 19748.16 | F25: =ОСБ!I83 -> 0 | G25: У нас краткосрочный кредит
C26: в том числе: поставщики и подрядчики (60, 76) | D26: 621 | E26: =ОСБ!E77 -> 0 | F26: =ОСБ!I77 -> 0
C27: задолженность перед персоналом организации (70) | D27: 624 | E27: =ОСБ!E100 -> 0 | F27: =ОСБ!I100 -> 0
C28: задолженность перед государственными внебюджетными фондами (69) | D28: 625 | E28: =ОСБ!E95 -> 43480.97 | F28: =ОСБ!I95 -> 43480.97
C29: задолженность по налогам и сборам (68) | D29: 626 | E29: =ОСБ!E91 -> 114466.7 | F29: =ОСБ!I91 -> 71188.633
C30: Прочие краткосрочные обязательства | D30: 660 | E30: =0 -> 0 | F30: =ОСБ!I62 -> 193194.88 | G30: Мне не хватало денег что бы закрыть все расчеты, особенно после вычетов НДФЛ и налога на имущество
C31: Итого по разделу V | D31: 690 | E31: =SUM(E25:E29) -> 177695.83 | F31: =SUM(F25:F30) -> 307864.48
C32: БАЛАНС (сумма строк 490+590+690) | D32: 700 | E32: =E31+E24 -> 5000631 | F32: =F31+F24 -> 4621145.3
E34: =E17-E32 -> 0 | F34: =F32-F17 -> 0

Sheet Форма 2
B2: Отчет о прибылях и убытках, форма №2
B3: Показатель | C3: Код показателя | D3: За отчетный период
B4: Доходы и расходы по обычным видам деятельности
B5: Выручка (нетто) от продажи товаров, продукции, работ, услуг (за минусом налога на добавленную стоимость, акцизов и аналогичных обязательных платежей) | C5: 10 | D5: 0 | E5: В 4 квартале продукция не отгружалась (нет оборота по Кт 90-1). Счёт 90-1 в ОСБ отсутствует.
B6: Себестоимость проданных товаров, продукции, работ, услуг | C6: 20 | D6: 0 | E6: Нет продаж → нет списания себестоимости (Дт 90-2 с Кт 43 отсутствует).
B7: Валовый убыток | C7: 29 | D7: =D5-D6 -> 0
B8: Коммерческие расходы (44) | C8: 30 | D8: =ОСБ!F112 -> 81081.333 | E8: Оборот по дебету счёта 90-2 в части коммерческих расходов (строка 109 ОСБ). Это сумма, списанная со счёта 44.
B9: Управленческие расходы | C9: 40 | D9: =ОСБ!F113 -> 405830.22 | E9: Оборот по дебету счёта 90-2 в части общехозяйственных расходов (строка 110 ОСБ). Это сумма, списанная со счёта 26.
B10: Убыток от продаж (010-020-030-040) | C10: 50 | D10: =-(D7-D9-D8) -> 486911.56 | E10: Разница между валовой прибылью и расходами на продажу и управление. В ОСБ этот же результат отражён как оборот Дт 99 Кт 90-9 (строка 111 ОСБ, сумма G114).
B11: Операционные доходы и расходы
B12: Проценты к уплате | C12: 70 | D12: =ОСБ!F116 -> 1922 | E12: Оборот по дебету счёта 91-2 (строка 113 ОСБ). Это проценты по кредиту.
B13: Прочие операционные доходы | C13: 90 | D13: =0 -> 0 | E13: Оборотов по Кт 91-1 нет.
B14: Прочие операционные расходы | C14: 100 | D14: 0 | E14: Кроме процентов других расходов по сч. 91-2 нет.
B15: 3. Внереализационные доходы и расходы
B16: Прибыль до налогообложения (строки 050 + 060 – 070 + 080 + 090 – 100 + 120 – 130) | C16: 140 | D16: =D10+D12 -> 488833.56 | E16: Сумма убытка от продаж и процентов к уплате. В ОСБ это сумма дебетовых оборотов по сч. 99 в корреспонденции с 90-9 и 91-9
B17: Налог на прибыль и иные аналогичные обязательные платежи (налог на имущество) | C17: 150 | D17: =ОСБ!F122 -> 20820.82
B18: Убыток от обычной деятельности | C18: 160 | D18: =D16+D17 -> 509654.38
B19: Чистаый убыток отчетного периода (160+170-180) | C19: 190 | D19: =D18 -> 509654.38 | E19: Соответствует сумме, списанной на счёт 84
E21: Мы в убытке
D22: =D19-'Книга учета хоз. операций'!G85 -> 0

Sheet Финансовое состояние
C2: на начало отченого периода | D2: на конец отченого периода | E2: Выводы
C3: Платежеспособность, %
B4: DAR | C4: ='Форма 1'!E31/'Форма 1'!E17 -> 0.035534682 | D4: ='Форма 1'!F31/'Форма 1'!F17 -> 0.066620819 | E4: Очень низкая доля обязательств в активах. Предприятие практически не зависит от заёмных средств. Финансовая устойчивость высокая.
B5: DER | C5: ='Форма 1'!E31/'Форма 1'!E24 -> 0.036843918 | D5: ='Форма 1'!F31/'Форма 1'!F24 -> 0.071375943 | E5: На 1 рубль собственного капитала приходится 7 копеек заёмного. Минимальный финансовый риск.
B6: TIE | C6: =IF('Форма 2'!D12=0,"Нет исходных данных",-'Форма 2'!D10/'Форма 2'!D12) -> -253.33588 | E6: Отрицательное значение из-за убытка. Операционная деятельность не покрывает проценты. Необходимо восстановление прибыльности.
B7: Ликвидность
B8: CR | C8: ='Форма 1'!E16/'Форма 1'!E31 -> 6.8376804 | D8: ='Форма 1'!F16/'Форма 1'!F31 -> 2.3273468 | E8: Текущая ликвидность выше нормы (1,5–2). Оборотных активов достаточно для погашения краткосрочных обязательств.
B9: QR | C9: =('Форма 1'!E12+'Форма 1'!E13+'Форма 1'!E14+'Форма 1'!E15)/'Форма 1'!E32 -> 0.038200639 | D9: =('Форма 1'!F12+'Форма 1'!F13+'Форма 1'!F14+'Форма 1'!F15)/'Форма 1'!F32 -> 0.0095172425 | E9: Критически низкая быстрая ликвидность. Практически отсутствуют ликвидные активы (деньги + дебиторка) для срочного погашения долгов.
B10: AR | C10: =('Форма 1'!E13+'Форма 1'!E14+'Форма 1'!E15)/'Форма 1'!E31 -> 1.0733022 | D10: =('Форма 1'!F13+'Форма 1'!F14+'Форма 1'!F15)/'Форма 1'!F31 -> 0.12797706 | E10: Абсолютная ликвидность ниже нормы (≥0,2). Денежных средств недостаточно для немедленной оплаты обязательств.
B11: NWC, тыс. руб. | C11: ='Форма 1'!E16-'Форма 1'!E31 -> 1037331.5 | D11: ='Форма 1'!F16-'Форма 1'!F31 -> 408642.93 | E11: Чистый оборотный капитал положительный. Предприятие имеет собственные оборотные средства, краткосрочная платёжеспособность обеспечена.
B12: Рентабельность, %
B13: ROA | C13: =-'Форма 2'!D19/'Форма 1'!E17 -> -0.10191801 | D13: =-'Форма 2'!D19/'Форма 1'!F17 -> -0.11028746 | E13: Убыточность активов. Каждый рубль активов приносит 11 копеек убытка. Эффективность использования имущества низкая.
B14: ROE | C14: =-'Форма 2'!D19/'Форма 1'!E24 -> -0.10567307 | D14: =-'Форма 2'!D19/'Форма 1'!F24 -> -0.11815933 | E14: Убыточность собственного капитала. Собственники не получают отдачи на вложенные средства.
B15: ROIC | C15: =-('Форма 2'!D19+'Форма 2'!D12*(1-0.2))/('Форма 1'!E24+'Форма 1'!E29) -> -0.10353461 | D15: =-('Форма 2'!D19+'Форма 2'!D12*(1-0.2))/('Форма 1'!F24+'Форма 1'!F29) -> -0.11659153 | E15: Инвестированный капитал используется неэффективно, совокупная отдача отрицательная.
B16: GPM | C16: н.д | E16: Валовая рентабельность не рассчитывается из-за отсутствия выручки.
B17: Деловая активность
B18: RT | C18: =1 -> 1 | E18: Оборачиваемость дебиторской задолженности условно равна 1 (дебиторка отсутствует или минимальна). Покупатели платят сразу.
B19: CP, день | C19: 0 | E19: Период инкассации дебиторской задолженности нулевой, что подтверждает отсутствие коммерческого кредитования.
B20: Риск банкротства Zo | C20: =1.2*C21+1.4*C22+3.3*C23+0.6*C24+0.999*C25 -> 4.1628169 | E20: Значение >2,9 указывает на низкую вероятность банкротства. Несмотря на убытки, структура баланса (высокий собственный капитал, низкие долги) обеспечивает финансовую устойчивость.
B21: x1 | C21: ='Форма 1'!E16/'Форма 1'!E17 -> 0.2429748
B22: x2 | C22: =-('Форма 1'!F22-'Форма 1'!F23)/'Форма 1'!F17 -> 0.084085112
B23: x3 | C23: =-'Форма 2'!D16/'Форма 1'!F17 -> -0.10578191
B24: x4 | C24: ='Форма 1'!E16/'Форма 1'!E31 -> 6.8376804
B25: x5 | C25: ='Форма 2'!D5/'Форма 1'!F17 -> 0
